pyscilloscope/__init__.py
pyscilloscope/serial_scope.py
pyscilloscope/server_side_event_scope.py
pyscilloscope-0.0.3.dist-info/METADATA
pyscilloscope-0.0.3.dist-info/WHEEL
pyscilloscope-0.0.3.dist-info/top_level.txt
pyscilloscope-0.0.3.dist-info/RECORD
