Metadata-Version: 2.1
Name: pyscilloscope
Version: 0.0.3
Summary: Pyscilloscope is a simple, serial-based data viewing GUI
Home-page: https://github.com/danaukes/code_pyscilloscope
Author: Dan Aukes
Author-email: danaukes@danaukes.com
License: MIT
Platform: UNKNOWN
Classifier: Programming Language :: Python
Classifier: Programming Language :: Python :: 3
